.coveragerc
CONTRIBUTING.rst
LICENSE.rst
MANIFEST.in
PULL_REQUEST_TEMPLATE.rst
README.rst
requirements-docs.txt
requirements.txt
setup.cfg
setup.py
style_guide.rst
nept/__init__.py
nept/co_occurrence.py
nept/decoding.py
nept/lfp_filtering.py
nept/loaders_mclust.py
nept/loaders_medpc.py
nept/loaders_neuralynx.py
nept/place_fields.py
nept/tuning_curves.py
nept/utils.py
nept.egg-info/PKG-INFO
nept.egg-info/SOURCES.txt
nept.egg-info/dependency_links.txt
nept.egg-info/requires.txt
nept.egg-info/top_level.txt
nept/core/__init__.py
nept/core/analogsignal.py
nept/core/epoch.py
nept/core/localfieldpotential.py
nept/core/neurons.py
nept/core/position.py
nept/core/spiketrain.py
tests/!roborats
tests/test_analogsignal.py
tests/test_co_occurrence.py
tests/test_decoding.py
tests/test_epoch.py
tests/test_fields.py
tests/test_lfp_filtering.py
tests/test_loaders_medpc.py
tests/test_localfieldpotential.py
tests/test_neurons.py
tests/test_position.py
tests/test_spiketrain.py
tests/test_tuning_curve.py
tests/test_utils.py