Metadata-Version: 1.0
Name: nept
Version: 0.1.0
Summary: Neuroelectrophysiology tools
Home-page: https://github.com/vandermeerlab/nept
Author: Emily Irvine
Author-email: emilymirvine@gmail.com
License: UNKNOWN
Platform: UNKNOWN
